pioreactor_relay_plugin/__init__.py
pioreactor_relay_plugin/additional_config.ini
pioreactor_relay_plugin/test_relay.py
pioreactor_relay_plugin/ui/contrib/jobs/relay.yaml
pioreactor_relay_plugin-0.8.0.dist-info/licenses/LICENSE.txt
pioreactor_relay_plugin-0.8.0.dist-info/METADATA
pioreactor_relay_plugin-0.8.0.dist-info/WHEEL
pioreactor_relay_plugin-0.8.0.dist-info/entry_points.txt
pioreactor_relay_plugin-0.8.0.dist-info/top_level.txt
pioreactor_relay_plugin-0.8.0.dist-info/RECORD
