Metadata-Version: 2.4
Name: pioreactor-relay-plugin
Version: 0.8.0
Summary: Turn the PWM channels into a simple on/off relay for additional hardware.
Home-page: https://github.com/CamDavidsonPilon/pioreactor-relay-plugin
Author: Kelly Tran, Pioreactor
Author-email: cam@pioreactor.com
License: MIT
License-File: LICENSE.txt
Dynamic: author
Dynamic: author-email
Dynamic: description
Dynamic: description-content-type
Dynamic: home-page
Dynamic: license
Dynamic: license-file
Dynamic: summary
